<materials>
  <material name="multi_box_material">
    <attributes>
      <attribute name="ambient" value="0.5f,  0.5f, 0.5f, 1.0f"/>
      <attribute name="diffuse" value="0.9f, 0.9f, 0.9f, 1.0f"/>
      <attribute name="specular" value="1.0f, 1.0f, 1.0f, 32.0f"/>
      <attribute name="emissive" value="0.0f, 0.0f, 0.0f, 1.0f"/>
    </attributes>

    <pipelines>
      <pipeline name="multi_objects_pipeline"/>
      <pipeline name="shadow_map_multi_objects_pipeline" usage="shadow_map"/>
    </pipelines>
    
  </material>


  
</materials>
